JthonsTorches/JthonsTorches.py
JthonsTorches/__init__.py
jthonstorches-1.0.1.dist-info/licenses/License.license
jthonstorches-1.0.1.dist-info/METADATA
jthonstorches-1.0.1.dist-info/WHEEL
jthonstorches-1.0.1.dist-info/top_level.txt
jthonstorches-1.0.1.dist-info/RECORD
