Metadata-Version: 2.4
Name: JthonsTorches
Version: 1.0.1
Summary: I'd reckon that this library is pretty useful, right? Like, it's a Java IDE in Python! Who wouldn't want that?
Author: APomson6000UserWhoEats6000IrisFlowers
License-File: License.license
Dynamic: license-file
